gtfu/__init__.py
gtfu/__main__.py
gtfu/_api.py
gtfu/cli.py
gtfu/core.py
gtfu/util.py
gtfu-1.5.0.dist-info/LICENSE
gtfu-1.5.0.dist-info/METADATA
gtfu-1.5.0.dist-info/WHEEL
gtfu-1.5.0.dist-info/entry_points.txt
gtfu-1.5.0.dist-info/RECORD
