Metadata-Version: 2.3
Name: gtfu
Version: 1.5.0
Summary: Command line tool to Get pageTitle From Url.
License: MIT
Author: seijinrosen
Author-email: 86702775+seijinrosen@users.noreply.github.com
Requires-Python: >=3.9,<4.0
Classifier: License :: OSI Approved :: MIT License
Classifier: Programming Language :: Python :: 3
Classifier: Programming Language :: Python :: 3.9
Classifier: Programming Language :: Python :: 3.10
Classifier: Programming Language :: Python :: 3.11
Classifier: Programming Language :: Python :: 3.12
Classifier: Programming Language :: Python :: 3.13
Requires-Dist: beautifulsoup4 (>=4.10.0,<5.0.0)
Requires-Dist: lxml (>=4.8,<6.0)
Requires-Dist: pyperclip (>=1.8.2,<2.0.0)
Requires-Dist: readchar (>=3.0.5,<5.0.0)
Requires-Dist: requests (>=2.27.1,<3.0.0)
Requires-Dist: rich (>=12.0.1,<14.0.0)
Project-URL: Documentation, https://github.com/seijinrosen/gtfu
Project-URL: Homepage, https://github.com/seijinrosen
Project-URL: Repository, https://github.com/seijinrosen/gtfu
